MANIFEST.in
README.md
cirrus.conf
requirements.txt
setup.py
test-requirements.txt
src/golems/__init__.py
src/golems.egg-info/PKG-INFO
src/golems.egg-info/SOURCES.txt
src/golems.egg-info/dependency_links.txt
src/golems.egg-info/requires.txt
src/golems.egg-info/top_level.txt