Metadata-Version: 1.1
Name: golems
Version: 0.0.0
Summary: queued container execution
Home-page: https://github.com/evansde77/golems
Author: evansde77@gmail.com
Author-email: evansde77@gmail.com
License: UNKNOWN
Platform: UNKNOWN
Provides: golems
